fordpip/__init__.py
fordpip/start.py
fordpip/test.py
fordpip-1.0.0.dist-info/METADATA
fordpip-1.0.0.dist-info/WHEEL
fordpip-1.0.0.dist-info/licenses/LICENSE
fordpip-1.0.0.dist-info/RECORD
