Metadata-Version: 2.1
Name: fordpip
Version: 0.0.1
Summary: A ford-pip package
Author-email: Labic <labicmma@gmail.com>
Project-URL: Homepage, https://github.com/pypa/sampleproject
Project-URL: Issues, https://github.com/pypa/sampleproject/issues
Classifier: Programming Language :: Python :: 3
Classifier: License :: OSI Approved :: MIT License
Classifier: Operating System :: OS Independent
Requires-Python: >=3.8
License-File: LICENSE
Requires-Dist: matplotlib>=3.5.2
Requires-Dist: networkx>=2.8.1
Requires-Dist: nltk>=3.7
Requires-Dist: openpyxl>=3.0.9
Requires-Dist: pandas>=1.4.2
Requires-Dist: Pillow>=9.1.1
Requires-Dist: plotly>=5.8.0
Requires-Dist: requests>=2.27.1
Requires-Dist: twython>=3.9.1
Requires-Dist: xlrd>=2.0.1
Requires-Dist: xlwt>=1.3.0
Requires-Dist: colored>=1.4.4
Requires-Dist: dlib>=19.24.0
Requires-Dist: face_recognition>=1.3.0
Requires-Dist: mediapipe>=0.9.0.1
Requires-Dist: numpy>=1.23.4
Requires-Dist: pandas>=1.5.0
Requires-Dist: Pillow>=9.4.0
Requires-Dist: progress>=1.6
Requires-Dist: scikit_learn==1.1.3
Requires-Dist: seaborn
Requires-Dist: ftfy
Requires-Dist: regex
Requires-Dist: tqdm
Requires-Dist: open_clip_torch
Requires-Dist: umap-learn
Requires-Dist: hdbscan==0.8.29
Requires-Dist: youtube-transcript-api
Requires-Dist: python-youtube
Requires-Dist: pytube
Requires-Dist: pythumb
